LICENSE
MANIFEST.in
README
chiki_base.py
setup.py
Chiki_Base.egg-info/PKG-INFO
Chiki_Base.egg-info/SOURCES.txt
Chiki_Base.egg-info/dependency_links.txt
Chiki_Base.egg-info/not-zip-safe
Chiki_Base.egg-info/requires.txt
Chiki_Base.egg-info/top_level.txt
chiki_base.egg-info/PKG-INFO
chiki_base.egg-info/SOURCES.txt
chiki_base.egg-info/dependency_links.txt
chiki_base.egg-info/not-zip-safe
chiki_base.egg-info/requires.txt
chiki_base.egg-info/top_level.txt