Metadata-Version: 1.0
Name: chiki-base
Version: 0.0.3
Summary: chiki base libs.
Home-page: https://github.com/endsh/chiki-base
Author: Linshao
Author-email: 438985635@qq.com
License: UNKNOWN
Platform: any
